README.rst
setup.cfg
setup.py
snorky/__init__.py
snorky/client.py
snorky/hashable.py
snorky/log.py
snorky/service_registry.py
snorky/timeout.py
snorky/types.py
snorky.egg-info/PKG-INFO
snorky.egg-info/SOURCES.txt
snorky.egg-info/dependency_links.txt
snorky.egg-info/requires.txt
snorky.egg-info/top_level.txt
snorky/backend/__init__.py
snorky/backend/django/__init__.py
snorky/backend/django/rest_framework.py
snorky/request_handlers/__init__.py
snorky/request_handlers/http.py
snorky/request_handlers/sockjs.py
snorky/request_handlers/websocket.py
snorky/services/__init__.py
snorky/services/base.py
snorky/services/chat.py
snorky/services/cursors.py
snorky/services/messaging.py
snorky/services/pubsub.py
snorky/services/datasync/__init__.py
snorky/services/datasync/backend.py
snorky/services/datasync/dealers.py
snorky/services/datasync/delta.py
snorky/services/datasync/frontend.py
snorky/services/datasync/subscription.py
snorky/services/datasync/managers/__init__.py
snorky/services/datasync/managers/dealer.py
snorky/services/datasync/managers/subscription.py
snorky/tests/__init__.py
snorky/tests/test_broadcast_dealer.py
snorky/tests/test_chat.py
snorky/tests/test_complex_hashable.py
snorky/tests/test_cursor.py
snorky/tests/test_datasync_service.py
snorky/tests/test_dealer.py
snorky/tests/test_dealer_manager.py
snorky/tests/test_filter_dealer.py
snorky/tests/test_filters.py
snorky/tests/test_messaging.py
snorky/tests/test_multidict.py
snorky/tests/test_pubsub.py
snorky/tests/test_rpc.py
snorky/tests/test_rpc_magic.py
snorky/tests/test_service_registry.py
snorky/tests/test_simple_dealer.py
snorky/tests/test_subscription.py
snorky/tests/test_subscription_manager.py
snorky/tests/test_timeout.py
snorky/tests/test_update_cases_dealer.py
snorky/tests/utils/__init__.py
snorky/tests/utils/rpc.py
snorky/tests/utils/timeout.py